nlp/__init__.py
nlp/arrow_dataset.py
nlp/arrow_reader.py
nlp/arrow_writer.py
nlp/builder.py
nlp/features.py
nlp/hf_api.py
nlp/info.py
nlp/inspect.py
nlp/load.py
nlp/metric.py
nlp/naming.py
nlp/splits.py
nlp/commands/__init__.py
nlp/commands/convert.py
nlp/commands/download.py
nlp/commands/dummy_data.py
nlp/commands/env.py
nlp/commands/run_beam.py
nlp/commands/test.py
nlp/commands/user.py
nlp/datasets/__init__.py
nlp/datasets/aeslc/__init__.py
nlp/datasets/aeslc/07680670860670fe2b03310206dd9150b2fa5464b43ee12f634c9f4ab212177e/__init__.py
nlp/datasets/aeslc/07680670860670fe2b03310206dd9150b2fa5464b43ee12f634c9f4ab212177e/aeslc.py
nlp/datasets/aeslc/42e9cbf0c1a798b1c6d314d56e2086655399a60f12d80c5ed1a8dd15dfc35e8e/__init__.py
nlp/datasets/aeslc/42e9cbf0c1a798b1c6d314d56e2086655399a60f12d80c5ed1a8dd15dfc35e8e/aeslc.py
nlp/datasets/aeslc/6f555f694c47cd0162839e277e1a73106430f7dc1fdb337ca12afdd17d8f0bbe/__init__.py
nlp/datasets/aeslc/6f555f694c47cd0162839e277e1a73106430f7dc1fdb337ca12afdd17d8f0bbe/aeslc.py
nlp/datasets/aeslc/800a8488b54560e929a3cfbd4febc40624aaca1e7862f4066c640b1edcf816d3/__init__.py
nlp/datasets/aeslc/800a8488b54560e929a3cfbd4febc40624aaca1e7862f4066c640b1edcf816d3/aeslc.py
nlp/datasets/ai2_arc/__init__.py
nlp/datasets/ai2_arc/0b088a9abf143896951217da0e3ff6caf75c0bdf0a9b2661234111866236b55a/__init__.py
nlp/datasets/ai2_arc/0b088a9abf143896951217da0e3ff6caf75c0bdf0a9b2661234111866236b55a/ai2_arc.py
nlp/datasets/ai2_arc/e57c41907a8bb31e7903077a85325e4ed646e174823462469a1bf8388d1f471e/__init__.py
nlp/datasets/ai2_arc/e57c41907a8bb31e7903077a85325e4ed646e174823462469a1bf8388d1f471e/ai2_arc.py
nlp/datasets/allocine/__init__.py
nlp/datasets/allocine/db8120b87276d60a04c8f5f734698ecc094b107e23b60a449e31639f24867cc9/__init__.py
nlp/datasets/allocine/db8120b87276d60a04c8f5f734698ecc094b107e23b60a449e31639f24867cc9/allocine.py
nlp/datasets/anli/__init__.py
nlp/datasets/anli/24fe36e048c09ee545de3a77d1f74f58002385b647d78e7d2dc401660255c2ad/__init__.py
nlp-0.3.0.dist-info/AUTHORS
nlp-0.3.0.dist-info/LICENSE
nlp-0.3.0.dist-info/METADATA
nlp-0.3.0.dist-info/WHEEL
nlp-0.3.0.dist-info/top_level.txt
nlp-0.3.0.dist-info/RECORD
